{
  "generated_at": "2026-07-02T04:29:18.083105Z",
  "report_type": "calibration_report",
  "status": "ok",
  "input_path": "data/oos_predictions_with_labels.csv",
  "sample_count": 71,
  "valid_sample_count": 71,
  "dropped_invalid_rows": 0,
  "probability_column": "y_prob",
  "target_column": "y_true",
  "brier": 0.26184830380184726,
  "ece": 0.19499773926825262,
  "mce": 0.6297852117556768,
  "n_bins": 10,
  "reliability_table": [
    {
      "bin_start": 0.0,
      "bin_end": 0.1,
      "count": 0,
      "avg_predicted_probability": null,
      "observed_win_rate": null,
      "calibration_gap": null
    },
    {
      "bin_start": 0.1,
      "bin_end": 0.2,
      "count": 0,
      "avg_predicted_probability": null,
      "observed_win_rate": null,
      "calibration_gap": null
    },
    {
      "bin_start": 0.2,
      "bin_end": 0.3,
      "count": 0,
      "avg_predicted_probability": null,
      "observed_win_rate": null,
      "calibration_gap": null
    },
    {
      "bin_start": 0.3,
      "bin_end": 0.4,
      "count": 2,
      "avg_predicted_probability": 0.37021478824432313,
      "observed_win_rate": 1.0,
      "calibration_gap": 0.6297852117556768
    },
    {
      "bin_start": 0.4,
      "bin_end": 0.5,
      "count": 45,
      "avg_predicted_probability": 0.46605431595124136,
      "observed_win_rate": 0.6,
      "calibration_gap": 0.13394568404875862
    },
    {
      "bin_start": 0.5,
      "bin_end": 0.6,
      "count": 23,
      "avg_predicted_probability": 0.5302441287653635,
      "observed_win_rate": 0.2608695652173913,
      "calibration_gap": 0.26937456354797223
    },
    {
      "bin_start": 0.6,
      "bin_end": 0.7,
      "count": 1,
      "avg_predicted_probability": 0.6379016792629167,
      "observed_win_rate": 1.0,
      "calibration_gap": 0.36209832073708326
    },
    {
      "bin_start": 0.7,
      "bin_end": 0.8,
      "count": 0,
      "avg_predicted_probability": null,
      "observed_win_rate": null,
      "calibration_gap": null
    },
    {
      "bin_start": 0.8,
      "bin_end": 0.9,
      "count": 0,
      "avg_predicted_probability": null,
      "observed_win_rate": null,
      "calibration_gap": null
    },
    {
      "bin_start": 0.9,
      "bin_end": 1.0,
      "count": 0,
      "avg_predicted_probability": null,
      "observed_win_rate": null,
      "calibration_gap": null
    }
  ],
  "warnings": [],
  "errors": [],
  "live_betting_allowed": false,
  "automated_wagering_allowed": false,
  "production_model_replacement_allowed": false
}