{
  "generated_at": "2026-06-11T14:15:39.437298+00:00",
  "status": "ok",
  "input_files": {
    "prediction": {
      "path": "report/prediction.json",
      "exists": true,
      "error": ""
    },
    "finalized_games": {
      "path": "data/finalized_games.csv",
      "exists": true,
      "rows": 986,
      "error": ""
    },
    "market_odds_history": {
      "path": "data/market_odds_history.csv",
      "exists": true,
      "rows": 36742,
      "error": ""
    }
  },
  "ledger_count": 65,
  "new_entries": 0,
  "live_stake_units": 0.0,
  "errors": [],
  "warnings": [],
  "recommendations": [
    "Ledger records paper trades only. Live stake remains zero."
  ]
}